{
  "flow_type": "template",
  "flow_name": "edit_in_person",
  "status": "released",
  "rows": [
    {
      "name": "parent_count",
      "type": "set_variable",
      "_nested_name": "parent_count"
    },
    {
      "name": "first_name",
      "value": "",
      "_translations": {
        "value": {}
      },
      "type": "set_variable",
      "_nested_name": "first_name"
    },
    {
      "name": "last_name",
      "value": "",
      "_translations": {
        "value": {}
      },
      "type": "set_variable",
      "_nested_name": "last_name"
    },
    {
      "name": "current_answer_1",
      "type": "set_variable",
      "_nested_name": "current_answer_1"
    },
    {
      "name": "current_answer_2",
      "type": "set_variable",
      "_nested_name": "current_answer_2"
    },
    {
      "name": "current_answer_3",
      "type": "set_variable",
      "_nested_name": "current_answer_3"
    },
    {
      "name": "current_answer_4",
      "type": "set_variable",
      "_nested_name": "current_answer_4"
    },
    {
      "name": "current_answer_5",
      "type": "set_variable",
      "_nested_name": "current_answer_5"
    },
    {
      "name": "current_answer_6",
      "type": "set_variable",
      "_nested_name": "current_answer_6"
    },
    {
      "name": "current_answer_7",
      "type": "set_variable",
      "_nested_name": "current_answer_7"
    },
    {
      "name": "current_answer_8",
      "type": "set_variable",
      "_nested_name": "current_answer_8"
    },
    {
      "name": "current_answer_9",
      "type": "set_variable",
      "_nested_name": "current_answer_9"
    },
    {
      "name": "current_answer_10",
      "type": "set_variable",
      "_nested_name": "current_answer_10"
    },
    {
      "name": "module_name",
      "type": "set_variable",
      "_nested_name": "module_name"
    },
    {
      "name": "challenge_postfix",
      "value": "_challenge",
      "_translations": {
        "value": {}
      },
      "type": "set_variable",
      "_nested_name": "challenge_postfix"
    },
    {
      "name": "challenge_field",
      "value": "@fields.current_module_no@local.challenge_postfix",
      "_translations": {
        "value": {}
      },
      "type": "set_variable",
      "_nested_name": "challenge_field",
      "_dynamicFields": {
        "value": [
          {
            "fullExpression": "@fields.current_module_no@local.challenge_postfix",
            "matchedExpression": "@fields.current_module_no",
            "type": "fields",
            "fieldName": "current_module_no"
          },
          {
            "fullExpression": "@fields.current_module_no@local.challenge_postfix",
            "matchedExpression": "@local.challenge_postfix",
            "type": "local",
            "fieldName": "challenge_postfix"
          }
        ]
      },
      "_dynamicDependencies": {
        "@fields.current_module_no": [
          "value"
        ],
        "@local.challenge_postfix": [
          "value"
        ]
      }
    },
    {
      "type": "data_items",
      "value": "report_answers",
      "_translations": {
        "value": {}
      },
      "action_list": [
        {
          "trigger": "data_changed",
          "action_id": "set_local",
          "args": [
            "current_answer_1",
            "@items[0].question_1"
          ],
          "_raw": "data_changed | set_local : current_answer_1: @items[0].question_1",
          "_cleaned": "data_changed | set_local : current_answer_1: @items[0].question_1"
        },
        {
          "trigger": "data_changed",
          "action_id": "set_local",
          "args": [
            "current_answer_2",
            "@items[0].question_2"
          ],
          "_raw": "data_changed | set_local : current_answer_2: @items[0].question_2",
          "_cleaned": "data_changed | set_local : current_answer_2: @items[0].question_2"
        },
        {
          "trigger": "data_changed",
          "action_id": "set_local",
          "args": [
            "current_answer_3",
            "@items[0].question_3"
          ],
          "_raw": "data_changed | set_local : current_answer_3: @items[0].question_3",
          "_cleaned": "data_changed | set_local : current_answer_3: @items[0].question_3"
        },
        {
          "trigger": "data_changed",
          "action_id": "set_local",
          "args": [
            "current_answer_4",
            "@items[0].question_4"
          ],
          "_raw": "data_changed | set_local : current_answer_4: @items[0].question_4",
          "_cleaned": "data_changed | set_local : current_answer_4: @items[0].question_4"
        },
        {
          "trigger": "data_changed",
          "action_id": "set_local",
          "args": [
            "current_answer_5",
            "@items[0].question_5"
          ],
          "_raw": "data_changed | set_local : current_answer_5: @items[0].question_5",
          "_cleaned": "data_changed | set_local : current_answer_5: @items[0].question_5"
        },
        {
          "trigger": "data_changed",
          "action_id": "set_local",
          "args": [
            "current_answer_6",
            "@items[0].question_6"
          ],
          "_raw": "data_changed | set_local : current_answer_6: @items[0].question_6",
          "_cleaned": "data_changed | set_local : current_answer_6: @items[0].question_6"
        },
        {
          "trigger": "data_changed",
          "action_id": "set_local",
          "args": [
            "current_answer_7",
            "@items[0].question_7"
          ],
          "_raw": "data_changed | set_local : current_answer_7: @items[0].question_7",
          "_cleaned": "data_changed | set_local : current_answer_7: @items[0].question_7"
        },
        {
          "trigger": "data_changed",
          "action_id": "set_local",
          "args": [
            "current_answer_8",
            "@items[0].question_8"
          ],
          "_raw": "data_changed | set_local : current_answer_8: @items[0].question_8",
          "_cleaned": "data_changed | set_local : current_answer_8: @items[0].question_8"
        },
        {
          "trigger": "data_changed",
          "action_id": "set_local",
          "args": [
            "current_answer_9",
            "@items[0].question_9"
          ],
          "_raw": "data_changed | set_local : current_answer_9: @items[0].question_9",
          "_cleaned": "data_changed | set_local : current_answer_9: @items[0].question_9"
        },
        {
          "trigger": "data_changed",
          "action_id": "set_local",
          "args": [
            "current_answer_10",
            "@items[0].question_10"
          ],
          "_raw": "data_changed | set_local : current_answer_10: @items[0].question_10",
          "_cleaned": "data_changed | set_local : current_answer_10: @items[0].question_10"
        }
      ],
      "parameter_list": {
        "filter": "@item.id == @fields.current_report_no"
      },
      "name": "data_items_18",
      "_nested_name": "data_items_18",
      "_dynamicFields": {
        "parameter_list": {
          "filter": [
            {
              "fullExpression": "@item.id == @fields.current_report_no",
              "matchedExpression": "@item.id",
              "type": "item",
              "fieldName": "id"
            },
            {
              "fullExpression": "@item.id == @fields.current_report_no",
              "matchedExpression": "@fields.current_report_no",
              "type": "fields",
              "fieldName": "current_report_no"
            }
          ]
        }
      },
      "_dynamicDependencies": {
        "@item.id": [
          "parameter_list.filter"
        ],
        "@fields.current_report_no": [
          "parameter_list.filter"
        ]
      }
    },
    {
      "type": "data_items",
      "value": "@data.report_data",
      "_translations": {
        "value": {}
      },
      "action_list": [
        {
          "trigger": "data_changed",
          "action_id": "set_local",
          "args": [
            "module_name",
            "@items[0].name"
          ],
          "_raw": "data_changed | set_local : module_name: @items[0].name",
          "_cleaned": "data_changed | set_local : module_name: @items[0].name"
        }
      ],
      "parameter_list": {
        "filter": "@item.id == @fields.current_report_id",
        "limit": "1"
      },
      "name": "data_items_19",
      "_nested_name": "data_items_19",
      "_dynamicFields": {
        "value": [
          {
            "fullExpression": "@data.report_data",
            "matchedExpression": "@data.report_data",
            "type": "data",
            "fieldName": "report_data"
          }
        ],
        "parameter_list": {
          "filter": [
            {
              "fullExpression": "@item.id == @fields.current_report_id",
              "matchedExpression": "@item.id",
              "type": "item",
              "fieldName": "id"
            },
            {
              "fullExpression": "@item.id == @fields.current_report_id",
              "matchedExpression": "@fields.current_report_id",
              "type": "fields",
              "fieldName": "current_report_id"
            }
          ]
        }
      },
      "_dynamicDependencies": {
        "@data.report_data": [
          "value"
        ],
        "@item.id": [
          "parameter_list.filter"
        ],
        "@fields.current_report_id": [
          "parameter_list.filter"
        ]
      }
    },
    {
      "type": "text",
      "name": "question_1",
      "value": "What was your role in the session?",
      "_translations": {
        "value": {
          "fil_ph": true,
          "ph_fil": true
        }
      },
      "_nested_name": "question_1"
    },
    {
      "name": "lead",
      "value": "Lead",
      "_translations": {
        "value": {
          "fil_ph": true,
          "ph_fil": true
        }
      },
      "type": "set_variable",
      "_nested_name": "lead"
    },
    {
      "name": "support",
      "value": "Support",
      "_translations": {
        "value": {
          "fil_ph": true,
          "ph_fil": true
        }
      },
      "type": "set_variable",
      "_nested_name": "support"
    },
    {
      "name": "answer_list_1",
      "value": [
        {
          "name": "lead",
          "text": "@local.lead"
        },
        {
          "name": "support",
          "text": "@local.support"
        }
      ],
      "type": "set_variable",
      "_nested_name": "answer_list_1",
      "_dynamicFields": {
        "value": {
          "0": {
            "text": [
              {
                "fullExpression": "@local.lead",
                "matchedExpression": "@local.lead",
                "type": "local",
                "fieldName": "lead"
              }
            ]
          },
          "1": {
            "text": [
              {
                "fullExpression": "@local.support",
                "matchedExpression": "@local.support",
                "type": "local",
                "fieldName": "support"
              }
            ]
          }
        }
      },
      "_dynamicDependencies": {
        "@local.lead": [
          "value.0.text"
        ],
        "@local.support": [
          "value.1.text"
        ]
      }
    },
    {
      "type": "radio_button_grid",
      "name": "answer_1",
      "value": "@local.current_answer_1",
      "_translations": {
        "value": {}
      },
      "parameter_list": {
        "item_width": "100%",
        "answer_list": "@local.answer_list_1"
      },
      "_nested_name": "answer_1",
      "_dynamicFields": {
        "value": [
          {
            "fullExpression": "@local.current_answer_1",
            "matchedExpression": "@local.current_answer_1",
            "type": "local",
            "fieldName": "current_answer_1"
          }
        ],
        "parameter_list": {
          "answer_list": [
            {
              "fullExpression": "@local.answer_list_1",
              "matchedExpression": "@local.answer_list_1",
              "type": "local",
              "fieldName": "answer_list_1"
            }
          ]
        }
      },
      "_dynamicDependencies": {
        "@local.current_answer_1": [
          "value"
        ],
        "@local.answer_list_1": [
          "parameter_list.answer_list"
        ]
      }
    },
    {
      "type": "display_group",
      "parameter_list": {
        "style": "column"
      },
      "condition": "@local.answer_1 == \"lead\" || @local.answer_1 == \"support\"",
      "rows": [
        {
          "type": "display_group",
          "parameter_list": {
            "style": "column"
          },
          "condition": "@local.answer_1 == \"lead\"",
          "rows": [
            {
              "type": "text",
              "name": "question_2",
              "value": "Date of Session Delivery?",
              "_translations": {
                "value": {
                  "fil_ph": true,
                  "ph_fil": true
                }
              },
              "_nested_name": "display_group_25.display_group_1.question_2"
            },
            {
              "type": "date_time_picker",
              "name": "answer_2",
              "value": "@local.current_answer_2",
              "_translations": {
                "value": {}
              },
              "parameter_list": {
                "type": "date"
              },
              "_nested_name": "display_group_25.display_group_1.answer_2",
              "_dynamicFields": {
                "value": [
                  {
                    "fullExpression": "@local.current_answer_2",
                    "matchedExpression": "@local.current_answer_2",
                    "type": "local",
                    "fieldName": "current_answer_2"
                  }
                ]
              },
              "_dynamicDependencies": {
                "@local.current_answer_2": [
                  "value"
                ]
              }
            },
            {
              "type": "text",
              "name": "question_3",
              "value": "How long did the session last?",
              "_translations": {
                "value": {
                  "fil_ph": true,
                  "ph_fil": true
                }
              },
              "_nested_name": "display_group_25.display_group_1.question_3"
            },
            {
              "type": "text_box",
              "name": "answer_3",
              "value": "@local.current_answer_3",
              "_translations": {
                "value": {}
              },
              "parameter_list": {
                "number_input": "true",
                "placeholder": "@global.minutes",
                "max_length": "3"
              },
              "_nested_name": "display_group_25.display_group_1.answer_3",
              "_dynamicFields": {
                "value": [
                  {
                    "fullExpression": "@local.current_answer_3",
                    "matchedExpression": "@local.current_answer_3",
                    "type": "local",
                    "fieldName": "current_answer_3"
                  }
                ],
                "parameter_list": {
                  "placeholder": [
                    {
                      "fullExpression": "@global.minutes",
                      "matchedExpression": "@global.minutes",
                      "type": "global",
                      "fieldName": "minutes"
                    }
                  ]
                }
              },
              "_dynamicDependencies": {
                "@local.current_answer_3": [
                  "value"
                ],
                "@global.minutes": [
                  "parameter_list.placeholder"
                ]
              }
            },
            {
              "type": "text",
              "name": "question_4",
              "value": "How much time did you spend on preparing for the session?",
              "_translations": {
                "value": {
                  "fil_ph": true,
                  "ph_fil": true
                }
              },
              "_nested_name": "display_group_25.display_group_1.question_4"
            },
            {
              "type": "text_box",
              "name": "answer_4",
              "value": "@local.current_answer_4",
              "_translations": {
                "value": {}
              },
              "parameter_list": {
                "number_input": "true",
                "placeholder": "@global.minutes",
                "max_length": "3"
              },
              "_nested_name": "display_group_25.display_group_1.answer_4",
              "_dynamicFields": {
                "value": [
                  {
                    "fullExpression": "@local.current_answer_4",
                    "matchedExpression": "@local.current_answer_4",
                    "type": "local",
                    "fieldName": "current_answer_4"
                  }
                ],
                "parameter_list": {
                  "placeholder": [
                    {
                      "fullExpression": "@global.minutes",
                      "matchedExpression": "@global.minutes",
                      "type": "global",
                      "fieldName": "minutes"
                    }
                  ]
                }
              },
              "_dynamicDependencies": {
                "@local.current_answer_4": [
                  "value"
                ],
                "@global.minutes": [
                  "parameter_list.placeholder"
                ]
              }
            },
            {
              "type": "text",
              "name": "question_5",
              "value": "Were you able to complete all the activities?",
              "_translations": {
                "value": {
                  "fil_ph": true,
                  "ph_fil": true
                }
              },
              "_nested_name": "display_group_25.display_group_1.question_5"
            },
            {
              "name": "yes",
              "value": "Yes",
              "_translations": {
                "value": {
                  "fil_ph": true,
                  "ph_fil": true
                }
              },
              "type": "set_variable",
              "_nested_name": "display_group_25.display_group_1.yes"
            },
            {
              "name": "no",
              "value": "No",
              "_translations": {
                "value": {
                  "fil_ph": true,
                  "ph_fil": true
                }
              },
              "type": "set_variable",
              "_nested_name": "display_group_25.display_group_1.no"
            },
            {
              "name": "answer_list_5",
              "value": [
                {
                  "name": "yes",
                  "text": "@local.yes"
                },
                {
                  "name": "no",
                  "text": "@local.no"
                }
              ],
              "type": "set_variable",
              "_nested_name": "display_group_25.display_group_1.answer_list_5",
              "_dynamicFields": {
                "value": {
                  "0": {
                    "text": [
                      {
                        "fullExpression": "@local.yes",
                        "matchedExpression": "@local.yes",
                        "type": "local",
                        "fieldName": "yes"
                      }
                    ]
                  },
                  "1": {
                    "text": [
                      {
                        "fullExpression": "@local.no",
                        "matchedExpression": "@local.no",
                        "type": "local",
                        "fieldName": "no"
                      }
                    ]
                  }
                }
              },
              "_dynamicDependencies": {
                "@local.yes": [
                  "value.0.text"
                ],
                "@local.no": [
                  "value.1.text"
                ]
              }
            },
            {
              "type": "radio_button_grid",
              "name": "answer_5",
              "value": "@local.current_answer_5",
              "_translations": {
                "value": {}
              },
              "parameter_list": {
                "item_width": "100%",
                "answer_list": "@local.answer_list_5"
              },
              "_nested_name": "display_group_25.display_group_1.answer_5",
              "_dynamicFields": {
                "value": [
                  {
                    "fullExpression": "@local.current_answer_5",
                    "matchedExpression": "@local.current_answer_5",
                    "type": "local",
                    "fieldName": "current_answer_5"
                  }
                ],
                "parameter_list": {
                  "answer_list": [
                    {
                      "fullExpression": "@local.answer_list_5",
                      "matchedExpression": "@local.answer_list_5",
                      "type": "local",
                      "fieldName": "answer_list_5"
                    }
                  ]
                }
              },
              "_dynamicDependencies": {
                "@local.current_answer_5": [
                  "value"
                ],
                "@local.answer_list_5": [
                  "parameter_list.answer_list"
                ]
              }
            },
            {
              "type": "text",
              "name": "question_6",
              "value": "What activities were you not able to complete? Why?",
              "_translations": {
                "value": {
                  "fil_ph": true,
                  "ph_fil": true
                }
              },
              "condition": "@local.answer_5 == \"no\"",
              "_nested_name": "display_group_25.display_group_1.question_6",
              "_dynamicFields": {
                "condition": [
                  {
                    "fullExpression": "@local.answer_5 == \"no\"",
                    "matchedExpression": "@local.answer_5",
                    "type": "local",
                    "fieldName": "answer_5"
                  }
                ]
              },
              "_dynamicDependencies": {
                "@local.answer_5": [
                  "condition"
                ]
              }
            },
            {
              "type": "text_box",
              "name": "answer_6",
              "value": "@local.current_answer_6",
              "_translations": {
                "value": {}
              },
              "condition": "@local.answer_5 == \"no\"",
              "_nested_name": "display_group_25.display_group_1.answer_6",
              "_dynamicFields": {
                "value": [
                  {
                    "fullExpression": "@local.current_answer_6",
                    "matchedExpression": "@local.current_answer_6",
                    "type": "local",
                    "fieldName": "current_answer_6"
                  }
                ],
                "condition": [
                  {
                    "fullExpression": "@local.answer_5 == \"no\"",
                    "matchedExpression": "@local.answer_5",
                    "type": "local",
                    "fieldName": "answer_5"
                  }
                ]
              },
              "_dynamicDependencies": {
                "@local.current_answer_6": [
                  "value"
                ],
                "@local.answer_5": [
                  "condition"
                ]
              }
            }
          ],
          "name": "display_group_1",
          "_nested_name": "display_group_25.display_group_1",
          "_dynamicFields": {
            "condition": [
              {
                "fullExpression": "@local.answer_1 == \"lead\"",
                "matchedExpression": "@local.answer_1",
                "type": "local",
                "fieldName": "answer_1"
              }
            ]
          },
          "_dynamicDependencies": {
            "@local.answer_1": [
              "condition"
            ]
          }
        },
        {
          "type": "display_group",
          "parameter_list": {
            "style": "column"
          },
          "condition": "@local.answer_5 == \"no\" || @local.answer_5 == \"yes\" || @local.answer_1 == \"support\"",
          "rows": [
            {
              "type": "text",
              "name": "confidence_header",
              "value": "How confident are you in the following?",
              "_translations": {
                "value": {
                  "fil_ph": true,
                  "ph_fil": true
                }
              },
              "parameter_list": {
                "style": "emphasised"
              },
              "_nested_name": "display_group_25.display_group_2.confidence_header"
            },
            {
              "name": "none",
              "value": "I have no confidence",
              "_translations": {
                "value": {
                  "fil_ph": true,
                  "ph_fil": true
                }
              },
              "type": "set_variable",
              "_nested_name": "display_group_25.display_group_2.none"
            },
            {
              "name": "low",
              "value": "My confidence is low",
              "_translations": {
                "value": {
                  "fil_ph": true,
                  "ph_fil": true
                }
              },
              "type": "set_variable",
              "_nested_name": "display_group_25.display_group_2.low"
            },
            {
              "name": "moderate",
              "value": "My confidence is moderate",
              "_translations": {
                "value": {
                  "fil_ph": true,
                  "ph_fil": true
                }
              },
              "type": "set_variable",
              "_nested_name": "display_group_25.display_group_2.moderate"
            },
            {
              "name": "high",
              "value": "My confidence is high",
              "_translations": {
                "value": {
                  "fil_ph": true,
                  "ph_fil": true
                }
              },
              "type": "set_variable",
              "_nested_name": "display_group_25.display_group_2.high"
            },
            {
              "name": "very_high",
              "value": "My confidence is very high",
              "_translations": {
                "value": {
                  "fil_ph": true,
                  "ph_fil": true
                }
              },
              "type": "set_variable",
              "_nested_name": "display_group_25.display_group_2.very_high"
            },
            {
              "name": "answer_list_confidence",
              "value": [
                {
                  "name": "none",
                  "text": "@local.none"
                },
                {
                  "name": "low",
                  "text": "@local.low"
                },
                {
                  "name": "moderate",
                  "text": "@local.moderate"
                },
                {
                  "name": "high",
                  "text": "@local.high"
                },
                {
                  "name": "very_high",
                  "text": "@local.very_high"
                }
              ],
              "type": "set_variable",
              "_nested_name": "display_group_25.display_group_2.answer_list_confidence",
              "_dynamicFields": {
                "value": {
                  "0": {
                    "text": [
                      {
                        "fullExpression": "@local.none",
                        "matchedExpression": "@local.none",
                        "type": "local",
                        "fieldName": "none"
                      }
                    ]
                  },
                  "1": {
                    "text": [
                      {
                        "fullExpression": "@local.low",
                        "matchedExpression": "@local.low",
                        "type": "local",
                        "fieldName": "low"
                      }
                    ]
                  },
                  "2": {
                    "text": [
                      {
                        "fullExpression": "@local.moderate",
                        "matchedExpression": "@local.moderate",
                        "type": "local",
                        "fieldName": "moderate"
                      }
                    ]
                  },
                  "3": {
                    "text": [
                      {
                        "fullExpression": "@local.high",
                        "matchedExpression": "@local.high",
                        "type": "local",
                        "fieldName": "high"
                      }
                    ]
                  },
                  "4": {
                    "text": [
                      {
                        "fullExpression": "@local.very_high",
                        "matchedExpression": "@local.very_high",
                        "type": "local",
                        "fieldName": "very_high"
                      }
                    ]
                  }
                }
              },
              "_dynamicDependencies": {
                "@local.none": [
                  "value.0.text"
                ],
                "@local.low": [
                  "value.1.text"
                ],
                "@local.moderate": [
                  "value.2.text"
                ],
                "@local.high": [
                  "value.3.text"
                ],
                "@local.very_high": [
                  "value.4.text"
                ]
              }
            },
            {
              "type": "text",
              "name": "question_7",
              "value": "On your knowledge about Talking about Feelings",
              "_translations": {
                "value": {
                  "fil_ph": true,
                  "ph_fil": true
                }
              },
              "_nested_name": "display_group_25.display_group_2.question_7"
            },
            {
              "type": "radio_button_grid",
              "name": "answer_7",
              "value": "@local.current_answer_7",
              "_translations": {
                "value": {}
              },
              "parameter_list": {
                "item_width": "100%",
                "answer_list": "@local.answer_list_confidence"
              },
              "_nested_name": "display_group_25.display_group_2.answer_7",
              "_dynamicFields": {
                "value": [
                  {
                    "fullExpression": "@local.current_answer_7",
                    "matchedExpression": "@local.current_answer_7",
                    "type": "local",
                    "fieldName": "current_answer_7"
                  }
                ],
                "parameter_list": {
                  "answer_list": [
                    {
                      "fullExpression": "@local.answer_list_confidence",
                      "matchedExpression": "@local.answer_list_confidence",
                      "type": "local",
                      "fieldName": "answer_list_confidence"
                    }
                  ]
                }
              },
              "_dynamicDependencies": {
                "@local.current_answer_7": [
                  "value"
                ],
                "@local.answer_list_confidence": [
                  "parameter_list.answer_list"
                ]
              }
            },
            {
              "type": "text",
              "name": "question_8",
              "value": "On your facilitation skills for Talking about Feelings",
              "_translations": {
                "value": {
                  "fil_ph": true,
                  "ph_fil": true
                }
              },
              "_nested_name": "display_group_25.display_group_2.question_8"
            },
            {
              "type": "radio_button_grid",
              "name": "answer_8",
              "value": "@local.current_answer_8",
              "_translations": {
                "value": {}
              },
              "parameter_list": {
                "item_width": "100%",
                "answer_list": "@local.answer_list_confidence"
              },
              "_nested_name": "display_group_25.display_group_2.answer_8",
              "_dynamicFields": {
                "value": [
                  {
                    "fullExpression": "@local.current_answer_8",
                    "matchedExpression": "@local.current_answer_8",
                    "type": "local",
                    "fieldName": "current_answer_8"
                  }
                ],
                "parameter_list": {
                  "answer_list": [
                    {
                      "fullExpression": "@local.answer_list_confidence",
                      "matchedExpression": "@local.answer_list_confidence",
                      "type": "local",
                      "fieldName": "answer_list_confidence"
                    }
                  ]
                }
              },
              "_dynamicDependencies": {
                "@local.current_answer_8": [
                  "value"
                ],
                "@local.answer_list_confidence": [
                  "parameter_list.answer_list"
                ]
              }
            },
            {
              "type": "text",
              "name": "coaching_header",
              "value": "Notes for Coaching",
              "_translations": {
                "value": {
                  "fil_ph": true,
                  "ph_fil": true
                }
              },
              "parameter_list": {
                "style": "emphasised"
              },
              "_nested_name": "display_group_25.display_group_2.coaching_header"
            },
            {
              "type": "text",
              "name": "question_9",
              "value": "What challenges did you face in delivering the module that you would like to discuss in the coaching session? Be specific.",
              "_translations": {
                "value": {
                  "fil_ph": true,
                  "ph_fil": true
                }
              },
              "_nested_name": "display_group_25.display_group_2.question_9"
            },
            {
              "type": "text_box",
              "name": "answer_9",
              "value": "@local.current_answer_9",
              "_translations": {
                "value": {}
              },
              "_nested_name": "display_group_25.display_group_2.answer_9",
              "_dynamicFields": {
                "value": [
                  {
                    "fullExpression": "@local.current_answer_9",
                    "matchedExpression": "@local.current_answer_9",
                    "type": "local",
                    "fieldName": "current_answer_9"
                  }
                ]
              },
              "_dynamicDependencies": {
                "@local.current_answer_9": [
                  "value"
                ]
              }
            },
            {
              "type": "text",
              "name": "question_10",
              "value": "What is your goal or what do you want to achieve or learn from the coaching session?",
              "_translations": {
                "value": {
                  "fil_ph": true,
                  "ph_fil": true
                }
              },
              "_nested_name": "display_group_25.display_group_2.question_10"
            },
            {
              "type": "text_box",
              "name": "answer_10",
              "value": "@local.current_answer_10",
              "_translations": {
                "value": {}
              },
              "_nested_name": "display_group_25.display_group_2.answer_10",
              "_dynamicFields": {
                "value": [
                  {
                    "fullExpression": "@local.current_answer_10",
                    "matchedExpression": "@local.current_answer_10",
                    "type": "local",
                    "fieldName": "current_answer_10"
                  }
                ]
              },
              "_dynamicDependencies": {
                "@local.current_answer_10": [
                  "value"
                ]
              }
            },
            {
              "exclude_from_translation": true,
              "type": "set_variable",
              "name": "set_variable_17",
              "_nested_name": "display_group_25.display_group_2.set_variable_17"
            },
            {
              "type": "data_items",
              "value": "@data.parents",
              "_translations": {
                "value": {}
              },
              "action_list": [
                {
                  "trigger": "data_changed",
                  "action_id": "set_local",
                  "args": [
                    "parent_count",
                    "@items.length"
                  ],
                  "_raw": "data_changed | set_local : parent_count : @items.length",
                  "_cleaned": "data_changed | set_local : parent_count : @items.length"
                }
              ],
              "parameter_list": {
                "filter": "@item.group_id == @field.current_group_no && @item.archived == false"
              },
              "condition": true,
              "exclude_from_translation": true,
              "name": "data_items_18",
              "_nested_name": "display_group_25.display_group_2.data_items_18",
              "_dynamicFields": {
                "value": [
                  {
                    "fullExpression": "@data.parents",
                    "matchedExpression": "@data.parents",
                    "type": "data",
                    "fieldName": "parents"
                  }
                ],
                "parameter_list": {
                  "filter": [
                    {
                      "fullExpression": "@item.group_id == @field.current_group_no && @item.archived == false",
                      "matchedExpression": "@item.group_id",
                      "type": "item",
                      "fieldName": "group_id"
                    },
                    {
                      "fullExpression": "@item.group_id == @field.current_group_no && @item.archived == false",
                      "matchedExpression": "@field.current_group_no",
                      "type": "field",
                      "fieldName": "current_group_no"
                    },
                    {
                      "fullExpression": "@item.group_id == @field.current_group_no && @item.archived == false",
                      "matchedExpression": "@item.archived",
                      "type": "item",
                      "fieldName": "archived"
                    }
                  ]
                }
              },
              "_dynamicDependencies": {
                "@data.parents": [
                  "value"
                ],
                "@item.group_id": [
                  "parameter_list.filter"
                ],
                "@field.current_group_no": [
                  "parameter_list.filter"
                ],
                "@item.archived": [
                  "parameter_list.filter"
                ]
              }
            },
            {
              "type": "display_group",
              "condition": "@local.answer_1 == \"lead\" && @local.parent_count == 0",
              "exclude_from_translation": true,
              "rows": [
                {
                  "type": "text",
                  "value": "No parents have been added to this group yet",
                  "_translations": {
                    "value": {}
                  },
                  "exclude_from_translation": false,
                  "name": "text_1",
                  "_nested_name": "display_group_25.display_group_2.display_group_19.text_1"
                }
              ],
              "name": "display_group_19",
              "_nested_name": "display_group_25.display_group_2.display_group_19",
              "_dynamicFields": {
                "condition": [
                  {
                    "fullExpression": "@local.answer_1 == \"lead\" && @local.parent_count == 0",
                    "matchedExpression": "@local.answer_1",
                    "type": "local",
                    "fieldName": "answer_1"
                  },
                  {
                    "fullExpression": "@local.answer_1 == \"lead\" && @local.parent_count == 0",
                    "matchedExpression": "@local.parent_count",
                    "type": "local",
                    "fieldName": "parent_count"
                  }
                ]
              },
              "_dynamicDependencies": {
                "@local.answer_1": [
                  "condition"
                ],
                "@local.parent_count": [
                  "condition"
                ]
              }
            },
            {
              "type": "text",
              "name": "question_11",
              "value": "Which of the parents in this group attended your in-person session?",
              "_translations": {
                "value": {
                  "fil_ph": true,
                  "ph_fil": true
                }
              },
              "condition": "@local.answer_1 == \"lead\" && @local.parent_count > 1",
              "_nested_name": "display_group_25.display_group_2.question_11",
              "_dynamicFields": {
                "condition": [
                  {
                    "fullExpression": "@local.answer_1 == \"lead\" && @local.parent_count > 1",
                    "matchedExpression": "@local.answer_1",
                    "type": "local",
                    "fieldName": "answer_1"
                  },
                  {
                    "fullExpression": "@local.answer_1 == \"lead\" && @local.parent_count > 1",
                    "matchedExpression": "@local.parent_count",
                    "type": "local",
                    "fieldName": "parent_count"
                  }
                ]
              },
              "_dynamicDependencies": {
                "@local.answer_1": [
                  "condition"
                ],
                "@local.parent_count": [
                  "condition"
                ]
              }
            },
            {
              "type": "data_items",
              "value": "parents",
              "parameter_list": {
                "filter": "@item.group_id == @field.current_group_no && @item.archived == false"
              },
              "condition": "@local.answer_1 == \"lead\" && @local.parent_count > 0",
              "rows": [
                {
                  "type": "display_group",
                  "parameter_list": {
                    "style": "column"
                  },
                  "rows": [
                    {
                      "type": "display_group",
                      "rows": [
                        {
                          "name": "first_name",
                          "value": "",
                          "_translations": {
                            "value": {}
                          },
                          "exclude_from_translation": true,
                          "type": "set_variable",
                          "_nested_name": "display_group_25.display_group_2.data_items_21.display_group_1_@item.id.display_group_1.first_name",
                          "_dynamicFields": {
                            "_nested_name": [
                              {
                                "fullExpression": "display_group_25.display_group_2.data_items_21.display_group_1_@item.id.display_group_1.first_name",
                                "matchedExpression": "@item.id.display_group_1.first_name",
                                "type": "item",
                                "fieldName": "id"
                              }
                            ]
                          },
                          "_dynamicDependencies": {
                            "@item.id.display_group_1.first_name": [
                              "_nested_name"
                            ]
                          }
                        },
                        {
                          "name": "last_name",
                          "value": "",
                          "_translations": {
                            "value": {}
                          },
                          "exclude_from_translation": true,
                          "type": "set_variable",
                          "_nested_name": "display_group_25.display_group_2.data_items_21.display_group_1_@item.id.display_group_1.last_name",
                          "_dynamicFields": {
                            "_nested_name": [
                              {
                                "fullExpression": "display_group_25.display_group_2.data_items_21.display_group_1_@item.id.display_group_1.last_name",
                                "matchedExpression": "@item.id.display_group_1.last_name",
                                "type": "item",
                                "fieldName": "id"
                              }
                            ]
                          },
                          "_dynamicDependencies": {
                            "@item.id.display_group_1.last_name": [
                              "_nested_name"
                            ]
                          }
                        },
                        {
                          "name": "first_name",
                          "value": "@item.first_name",
                          "_translations": {
                            "value": {}
                          },
                          "condition": "@item.first_name",
                          "exclude_from_translation": true,
                          "type": "set_variable",
                          "_nested_name": "display_group_25.display_group_2.data_items_21.display_group_1_@item.id.display_group_1.first_name",
                          "_dynamicFields": {
                            "value": [
                              {
                                "fullExpression": "@item.first_name",
                                "matchedExpression": "@item.first_name",
                                "type": "item",
                                "fieldName": "first_name"
                              }
                            ],
                            "condition": [
                              {
                                "fullExpression": "@item.first_name",
                                "matchedExpression": "@item.first_name",
                                "type": "item",
                                "fieldName": "first_name"
                              }
                            ],
                            "_nested_name": [
                              {
                                "fullExpression": "display_group_25.display_group_2.data_items_21.display_group_1_@item.id.display_group_1.first_name",
                                "matchedExpression": "@item.id.display_group_1.first_name",
                                "type": "item",
                                "fieldName": "id"
                              }
                            ]
                          },
                          "_dynamicDependencies": {
                            "@item.first_name": [
                              "value",
                              "condition"
                            ],
                            "@item.id.display_group_1.first_name": [
                              "_nested_name"
                            ]
                          }
                        },
                        {
                          "name": "last_name",
                          "value": "@item.last_name",
                          "_translations": {
                            "value": {}
                          },
                          "condition": "@item.last_name",
                          "exclude_from_translation": true,
                          "type": "set_variable",
                          "_nested_name": "display_group_25.display_group_2.data_items_21.display_group_1_@item.id.display_group_1.last_name",
                          "_dynamicFields": {
                            "value": [
                              {
                                "fullExpression": "@item.last_name",
                                "matchedExpression": "@item.last_name",
                                "type": "item",
                                "fieldName": "last_name"
                              }
                            ],
                            "condition": [
                              {
                                "fullExpression": "@item.last_name",
                                "matchedExpression": "@item.last_name",
                                "type": "item",
                                "fieldName": "last_name"
                              }
                            ],
                            "_nested_name": [
                              {
                                "fullExpression": "display_group_25.display_group_2.data_items_21.display_group_1_@item.id.display_group_1.last_name",
                                "matchedExpression": "@item.id.display_group_1.last_name",
                                "type": "item",
                                "fieldName": "id"
                              }
                            ]
                          },
                          "_dynamicDependencies": {
                            "@item.last_name": [
                              "value",
                              "condition"
                            ],
                            "@item.id.display_group_1.last_name": [
                              "_nested_name"
                            ]
                          }
                        },
                        {
                          "type": "text",
                          "value": "@local.first_name @local.last_name",
                          "_translations": {
                            "value": {}
                          },
                          "exclude_from_translation": true,
                          "style_list": [
                            "flex: 1"
                          ],
                          "name": "text_5",
                          "_nested_name": "display_group_25.display_group_2.data_items_21.display_group_1_@item.id.display_group_1.text_5",
                          "_dynamicFields": {
                            "value": [
                              {
                                "fullExpression": "@local.first_name @local.last_name",
                                "matchedExpression": "@local.first_name",
                                "type": "local",
                                "fieldName": "first_name"
                              },
                              {
                                "fullExpression": "@local.first_name @local.last_name",
                                "matchedExpression": "@local.last_name",
                                "type": "local",
                                "fieldName": "last_name"
                              }
                            ],
                            "_nested_name": [
                              {
                                "fullExpression": "display_group_25.display_group_2.data_items_21.display_group_1_@item.id.display_group_1.text_5",
                                "matchedExpression": "@item.id.display_group_1.text_5",
                                "type": "item",
                                "fieldName": "id"
                              }
                            ]
                          },
                          "_dynamicDependencies": {
                            "@local.first_name": [
                              "value"
                            ],
                            "@local.last_name": [
                              "value"
                            ],
                            "@item.id.display_group_1.text_5": [
                              "_nested_name"
                            ]
                          }
                        },
                        {
                          "type": "toggle_bar",
                          "name": "parent_attend",
                          "value": "@item.@fields.current_module_no",
                          "_translations": {
                            "value": {}
                          },
                          "action_list": [
                            {
                              "trigger": "changed",
                              "action_id": "set_item",
                              "args": [],
                              "_raw": "changed | set_item| @fields.current_module_no: this.value",
                              "_cleaned": "changed | set_item| @fields.current_module_no: this.value",
                              "params": {
                                "@fields.current_module_no": "this.value"
                              }
                            }
                          ],
                          "parameter_list": {
                            "show_icons": "false",
                            "variant": "ios"
                          },
                          "_nested_name": "display_group_25.display_group_2.data_items_21.display_group_1_@item.id.display_group_1.parent_attend",
                          "_dynamicFields": {
                            "value": [
                              {
                                "fullExpression": "@item.@fields.current_module_no",
                                "matchedExpression": "@fields.current_module_no",
                                "type": "fields",
                                "fieldName": "current_module_no"
                              }
                            ],
                            "action_list": {
                              "0": {
                                "_raw": [
                                  {
                                    "fullExpression": "changed | set_item| @fields.current_module_no: this.value",
                                    "matchedExpression": "@fields.current_module_no",
                                    "type": "fields",
                                    "fieldName": "current_module_no"
                                  }
                                ],
                                "_cleaned": [
                                  {
                                    "fullExpression": "changed | set_item| @fields.current_module_no: this.value",
                                    "matchedExpression": "@fields.current_module_no",
                                    "type": "fields",
                                    "fieldName": "current_module_no"
                                  }
                                ]
                              }
                            },
                            "_nested_name": [
                              {
                                "fullExpression": "display_group_25.display_group_2.data_items_21.display_group_1_@item.id.display_group_1.parent_attend",
                                "matchedExpression": "@item.id.display_group_1.parent_attend",
                                "type": "item",
                                "fieldName": "id"
                              }
                            ]
                          },
                          "_dynamicDependencies": {
                            "@fields.current_module_no": [
                              "value",
                              "action_list.0._raw",
                              "action_list.0._cleaned"
                            ],
                            "@item.id.display_group_1.parent_attend": [
                              "_nested_name"
                            ]
                          }
                        }
                      ],
                      "name": "display_group_1",
                      "_nested_name": "display_group_25.display_group_2.data_items_21.display_group_1_@item.id.display_group_1",
                      "_dynamicFields": {
                        "_nested_name": [
                          {
                            "fullExpression": "display_group_25.display_group_2.data_items_21.display_group_1_@item.id.display_group_1",
                            "matchedExpression": "@item.id.display_group_1",
                            "type": "item",
                            "fieldName": "id"
                          }
                        ]
                      },
                      "_dynamicDependencies": {
                        "@item.id.display_group_1": [
                          "_nested_name"
                        ]
                      }
                    },
                    {
                      "type": "display_group",
                      "parameter_list": {
                        "style": "column"
                      },
                      "condition": "@item.@fields.current_module_no",
                      "rows": [
                        {
                          "type": "text",
                          "value": "What challenges or successes did the parent experience during with their home activity for @local.module_name ? Were there any concerns?",
                          "_translations": {
                            "value": {
                              "fil_ph": true,
                              "ph_fil": true
                            }
                          },
                          "name": "text_1",
                          "_nested_name": "display_group_25.display_group_2.data_items_21.display_group_1_@item.id.display_group_2.text_1",
                          "_dynamicFields": {
                            "value": [
                              {
                                "fullExpression": "What challenges or successes did the parent experience during with their home activity for @local.module_name ? Were there any concerns?",
                                "matchedExpression": "@local.module_name",
                                "type": "local",
                                "fieldName": "module_name"
                              }
                            ],
                            "_nested_name": [
                              {
                                "fullExpression": "display_group_25.display_group_2.data_items_21.display_group_1_@item.id.display_group_2.text_1",
                                "matchedExpression": "@item.id.display_group_2.text_1",
                                "type": "item",
                                "fieldName": "id"
                              }
                            ]
                          },
                          "_dynamicDependencies": {
                            "@local.module_name": [
                              "value"
                            ],
                            "@item.id.display_group_2.text_1": [
                              "_nested_name"
                            ]
                          }
                        },
                        {
                          "type": "text_box",
                          "value": "@item.@local.challenge_field",
                          "_translations": {
                            "value": {}
                          },
                          "action_list": [
                            {
                              "trigger": "changed",
                              "action_id": "set_item",
                              "args": [],
                              "_raw": "changed | set_item| @local.challenge_field: this.value",
                              "_cleaned": "changed | set_item| @local.challenge_field: this.value",
                              "params": {
                                "@local.challenge_field": "this.value"
                              }
                            }
                          ],
                          "name": "text_box_2",
                          "_nested_name": "display_group_25.display_group_2.data_items_21.display_group_1_@item.id.display_group_2.text_box_2",
                          "_dynamicFields": {
                            "value": [
                              {
                                "fullExpression": "@item.@local.challenge_field",
                                "matchedExpression": "@local.challenge_field",
                                "type": "local",
                                "fieldName": "challenge_field"
                              }
                            ],
                            "action_list": {
                              "0": {
                                "_raw": [
                                  {
                                    "fullExpression": "changed | set_item| @local.challenge_field: this.value",
                                    "matchedExpression": "@local.challenge_field",
                                    "type": "local",
                                    "fieldName": "challenge_field"
                                  }
                                ],
                                "_cleaned": [
                                  {
                                    "fullExpression": "changed | set_item| @local.challenge_field: this.value",
                                    "matchedExpression": "@local.challenge_field",
                                    "type": "local",
                                    "fieldName": "challenge_field"
                                  }
                                ]
                              }
                            },
                            "_nested_name": [
                              {
                                "fullExpression": "display_group_25.display_group_2.data_items_21.display_group_1_@item.id.display_group_2.text_box_2",
                                "matchedExpression": "@item.id.display_group_2.text_box_2",
                                "type": "item",
                                "fieldName": "id"
                              }
                            ]
                          },
                          "_dynamicDependencies": {
                            "@local.challenge_field": [
                              "value",
                              "action_list.0._raw",
                              "action_list.0._cleaned"
                            ],
                            "@item.id.display_group_2.text_box_2": [
                              "_nested_name"
                            ]
                          }
                        }
                      ],
                      "name": "display_group_2",
                      "_nested_name": "display_group_25.display_group_2.data_items_21.display_group_1_@item.id.display_group_2",
                      "_dynamicFields": {
                        "condition": [
                          {
                            "fullExpression": "@item.@fields.current_module_no",
                            "matchedExpression": "@fields.current_module_no",
                            "type": "fields",
                            "fieldName": "current_module_no"
                          }
                        ],
                        "_nested_name": [
                          {
                            "fullExpression": "display_group_25.display_group_2.data_items_21.display_group_1_@item.id.display_group_2",
                            "matchedExpression": "@item.id.display_group_2",
                            "type": "item",
                            "fieldName": "id"
                          }
                        ]
                      },
                      "_dynamicDependencies": {
                        "@fields.current_module_no": [
                          "condition"
                        ],
                        "@item.id.display_group_2": [
                          "_nested_name"
                        ]
                      }
                    }
                  ],
                  "name": "display_group_1_@item.id",
                  "_nested_name": "display_group_25.display_group_2.data_items_21.display_group_1_@item.id",
                  "_dynamicFields": {
                    "name": [
                      {
                        "fullExpression": "display_group_1_@item.id",
                        "matchedExpression": "@item.id",
                        "type": "item",
                        "fieldName": "id"
                      }
                    ],
                    "_nested_name": [
                      {
                        "fullExpression": "display_group_25.display_group_2.data_items_21.display_group_1_@item.id",
                        "matchedExpression": "@item.id",
                        "type": "item",
                        "fieldName": "id"
                      }
                    ]
                  },
                  "_dynamicDependencies": {
                    "@item.id": [
                      "name",
                      "_nested_name"
                    ]
                  }
                }
              ],
              "name": "data_items_21",
              "_nested_name": "display_group_25.display_group_2.data_items_21",
              "_dynamicFields": {
                "parameter_list": {
                  "filter": [
                    {
                      "fullExpression": "@item.group_id == @field.current_group_no && @item.archived == false",
                      "matchedExpression": "@item.group_id",
                      "type": "item",
                      "fieldName": "group_id"
                    },
                    {
                      "fullExpression": "@item.group_id == @field.current_group_no && @item.archived == false",
                      "matchedExpression": "@field.current_group_no",
                      "type": "field",
                      "fieldName": "current_group_no"
                    },
                    {
                      "fullExpression": "@item.group_id == @field.current_group_no && @item.archived == false",
                      "matchedExpression": "@item.archived",
                      "type": "item",
                      "fieldName": "archived"
                    }
                  ]
                },
                "condition": [
                  {
                    "fullExpression": "@local.answer_1 == \"lead\" && @local.parent_count > 0",
                    "matchedExpression": "@local.answer_1",
                    "type": "local",
                    "fieldName": "answer_1"
                  },
                  {
                    "fullExpression": "@local.answer_1 == \"lead\" && @local.parent_count > 0",
                    "matchedExpression": "@local.parent_count",
                    "type": "local",
                    "fieldName": "parent_count"
                  }
                ]
              },
              "_dynamicDependencies": {
                "@item.group_id": [
                  "parameter_list.filter"
                ],
                "@field.current_group_no": [
                  "parameter_list.filter"
                ],
                "@item.archived": [
                  "parameter_list.filter"
                ],
                "@local.answer_1": [
                  "condition"
                ],
                "@local.parent_count": [
                  "condition"
                ]
              }
            }
          ],
          "name": "display_group_2",
          "_nested_name": "display_group_25.display_group_2",
          "_dynamicFields": {
            "condition": [
              {
                "fullExpression": "@local.answer_5 == \"no\" || @local.answer_5 == \"yes\" || @local.answer_1 == \"support\"",
                "matchedExpression": "@local.answer_5",
                "type": "local",
                "fieldName": "answer_5"
              },
              {
                "fullExpression": "@local.answer_5 == \"no\" || @local.answer_5 == \"yes\" || @local.answer_1 == \"support\"",
                "matchedExpression": "@local.answer_5",
                "type": "local",
                "fieldName": "answer_5"
              },
              {
                "fullExpression": "@local.answer_5 == \"no\" || @local.answer_5 == \"yes\" || @local.answer_1 == \"support\"",
                "matchedExpression": "@local.answer_1",
                "type": "local",
                "fieldName": "answer_1"
              }
            ]
          },
          "_dynamicDependencies": {
            "@local.answer_5": [
              "condition",
              "condition"
            ],
            "@local.answer_1": [
              "condition"
            ]
          }
        }
      ],
      "name": "display_group_25",
      "_nested_name": "display_group_25",
      "_dynamicFields": {
        "condition": [
          {
            "fullExpression": "@local.answer_1 == \"lead\" || @local.answer_1 == \"support\"",
            "matchedExpression": "@local.answer_1",
            "type": "local",
            "fieldName": "answer_1"
          },
          {
            "fullExpression": "@local.answer_1 == \"lead\" || @local.answer_1 == \"support\"",
            "matchedExpression": "@local.answer_1",
            "type": "local",
            "fieldName": "answer_1"
          }
        ]
      },
      "_dynamicDependencies": {
        "@local.answer_1": [
          "condition",
          "condition"
        ]
      }
    },
    {
      "type": "display_group",
      "parameter_list": {
        "sticky": "bottom"
      },
      "style_list": [
        "padding: 12px 24px"
      ],
      "rows": [
        {
          "type": "button",
          "name": "save",
          "value": "Save",
          "_translations": {
            "value": {
              "fil_ph": true,
              "ph_fil": true
            }
          },
          "action_list": [
            {
              "trigger": "click",
              "action_id": "set_data",
              "args": [],
              "_raw": "click | set_data |\n_list_id: report_answers,\n_id: @fields.current_report_no,\nquestion_1: @local.answer_1,\nquestion_2: @local.answer_2,\nquestion_3: @local.answer_3,\nquestion_4: @local.answer_4,\nquestion_5: @local.answer_5,\nquestion_6: @local.answer_6,\nquestion_7: @local.answer_7,\nquestion_8: @local.answer_8,\nquestion_9: @local.answer_9,\nquestion_10: @local.answer_10",
              "_cleaned": "click | set_data |\n_list_id: report_answers,\n_id: @fields.current_report_no,\nquestion_1: @local.answer_1,\nquestion_2: @local.answer_2,\nquestion_3: @local.answer_3,\nquestion_4: @local.answer_4,\nquestion_5: @local.answer_5,\nquestion_6: @local.answer_6,\nquestion_7: @local.answer_7,\nquestion_8: @local.answer_8,\nquestion_9: @local.answer_9,\nquestion_10: @local.answer_10",
              "params": {
                "_list_id": "report_answers",
                "_id": "@fields.current_report_no",
                "question_1": "@local.answer_1",
                "question_2": "@local.answer_2",
                "question_3": "@local.answer_3",
                "question_4": "@local.answer_4",
                "question_5": "@local.answer_5",
                "question_6": "@local.answer_6",
                "question_7": "@local.answer_7",
                "question_8": "@local.answer_8",
                "question_9": "@local.answer_9",
                "question_10": "@local.answer_10"
              }
            },
            {
              "trigger": "click",
              "action_id": "emit",
              "args": [
                "completed"
              ],
              "_raw": "click | emit: completed",
              "_cleaned": "click | emit: completed"
            }
          ],
          "_nested_name": "display_group_27.save",
          "_dynamicFields": {
            "action_list": {
              "0": {
                "_raw": [
                  {
                    "fullExpression": "click | set_data |\n_list_id: report_answers,\n_id: @fields.current_report_no,\nquestion_1: @local.answer_1,\nquestion_2: @local.answer_2,\nquestion_3: @local.answer_3,\nquestion_4: @local.answer_4,\nquestion_5: @local.answer_5,\nquestion_6: @local.answer_6,\nquestion_7: @local.answer_7,\nquestion_8: @local.answer_8,\nquestion_9: @local.answer_9,\nquestion_10: @local.answer_10",
                    "matchedExpression": "@fields.current_report_no",
                    "type": "fields",
                    "fieldName": "current_report_no"
                  },
                  {
                    "fullExpression": "click | set_data |\n_list_id: report_answers,\n_id: @fields.current_report_no,\nquestion_1: @local.answer_1,\nquestion_2: @local.answer_2,\nquestion_3: @local.answer_3,\nquestion_4: @local.answer_4,\nquestion_5: @local.answer_5,\nquestion_6: @local.answer_6,\nquestion_7: @local.answer_7,\nquestion_8: @local.answer_8,\nquestion_9: @local.answer_9,\nquestion_10: @local.answer_10",
                    "matchedExpression": "@local.answer_1",
                    "type": "local",
                    "fieldName": "answer_1"
                  },
                  {
                    "fullExpression": "click | set_data |\n_list_id: report_answers,\n_id: @fields.current_report_no,\nquestion_1: @local.answer_1,\nquestion_2: @local.answer_2,\nquestion_3: @local.answer_3,\nquestion_4: @local.answer_4,\nquestion_5: @local.answer_5,\nquestion_6: @local.answer_6,\nquestion_7: @local.answer_7,\nquestion_8: @local.answer_8,\nquestion_9: @local.answer_9,\nquestion_10: @local.answer_10",
                    "matchedExpression": "@local.answer_2",
                    "type": "local",
                    "fieldName": "answer_2"
                  },
                  {
                    "fullExpression": "click | set_data |\n_list_id: report_answers,\n_id: @fields.current_report_no,\nquestion_1: @local.answer_1,\nquestion_2: @local.answer_2,\nquestion_3: @local.answer_3,\nquestion_4: @local.answer_4,\nquestion_5: @local.answer_5,\nquestion_6: @local.answer_6,\nquestion_7: @local.answer_7,\nquestion_8: @local.answer_8,\nquestion_9: @local.answer_9,\nquestion_10: @local.answer_10",
                    "matchedExpression": "@local.answer_3",
                    "type": "local",
                    "fieldName": "answer_3"
                  },
                  {
                    "fullExpression": "click | set_data |\n_list_id: report_answers,\n_id: @fields.current_report_no,\nquestion_1: @local.answer_1,\nquestion_2: @local.answer_2,\nquestion_3: @local.answer_3,\nquestion_4: @local.answer_4,\nquestion_5: @local.answer_5,\nquestion_6: @local.answer_6,\nquestion_7: @local.answer_7,\nquestion_8: @local.answer_8,\nquestion_9: @local.answer_9,\nquestion_10: @local.answer_10",
                    "matchedExpression": "@local.answer_4",
                    "type": "local",
                    "fieldName": "answer_4"
                  },
                  {
                    "fullExpression": "click | set_data |\n_list_id: report_answers,\n_id: @fields.current_report_no,\nquestion_1: @local.answer_1,\nquestion_2: @local.answer_2,\nquestion_3: @local.answer_3,\nquestion_4: @local.answer_4,\nquestion_5: @local.answer_5,\nquestion_6: @local.answer_6,\nquestion_7: @local.answer_7,\nquestion_8: @local.answer_8,\nquestion_9: @local.answer_9,\nquestion_10: @local.answer_10",
                    "matchedExpression": "@local.answer_5",
                    "type": "local",
                    "fieldName": "answer_5"
                  },
                  {
                    "fullExpression": "click | set_data |\n_list_id: report_answers,\n_id: @fields.current_report_no,\nquestion_1: @local.answer_1,\nquestion_2: @local.answer_2,\nquestion_3: @local.answer_3,\nquestion_4: @local.answer_4,\nquestion_5: @local.answer_5,\nquestion_6: @local.answer_6,\nquestion_7: @local.answer_7,\nquestion_8: @local.answer_8,\nquestion_9: @local.answer_9,\nquestion_10: @local.answer_10",
                    "matchedExpression": "@local.answer_6",
                    "type": "local",
                    "fieldName": "answer_6"
                  },
                  {
                    "fullExpression": "click | set_data |\n_list_id: report_answers,\n_id: @fields.current_report_no,\nquestion_1: @local.answer_1,\nquestion_2: @local.answer_2,\nquestion_3: @local.answer_3,\nquestion_4: @local.answer_4,\nquestion_5: @local.answer_5,\nquestion_6: @local.answer_6,\nquestion_7: @local.answer_7,\nquestion_8: @local.answer_8,\nquestion_9: @local.answer_9,\nquestion_10: @local.answer_10",
                    "matchedExpression": "@local.answer_7",
                    "type": "local",
                    "fieldName": "answer_7"
                  },
                  {
                    "fullExpression": "click | set_data |\n_list_id: report_answers,\n_id: @fields.current_report_no,\nquestion_1: @local.answer_1,\nquestion_2: @local.answer_2,\nquestion_3: @local.answer_3,\nquestion_4: @local.answer_4,\nquestion_5: @local.answer_5,\nquestion_6: @local.answer_6,\nquestion_7: @local.answer_7,\nquestion_8: @local.answer_8,\nquestion_9: @local.answer_9,\nquestion_10: @local.answer_10",
                    "matchedExpression": "@local.answer_8",
                    "type": "local",
                    "fieldName": "answer_8"
                  },
                  {
                    "fullExpression": "click | set_data |\n_list_id: report_answers,\n_id: @fields.current_report_no,\nquestion_1: @local.answer_1,\nquestion_2: @local.answer_2,\nquestion_3: @local.answer_3,\nquestion_4: @local.answer_4,\nquestion_5: @local.answer_5,\nquestion_6: @local.answer_6,\nquestion_7: @local.answer_7,\nquestion_8: @local.answer_8,\nquestion_9: @local.answer_9,\nquestion_10: @local.answer_10",
                    "matchedExpression": "@local.answer_9",
                    "type": "local",
                    "fieldName": "answer_9"
                  },
                  {
                    "fullExpression": "click | set_data |\n_list_id: report_answers,\n_id: @fields.current_report_no,\nquestion_1: @local.answer_1,\nquestion_2: @local.answer_2,\nquestion_3: @local.answer_3,\nquestion_4: @local.answer_4,\nquestion_5: @local.answer_5,\nquestion_6: @local.answer_6,\nquestion_7: @local.answer_7,\nquestion_8: @local.answer_8,\nquestion_9: @local.answer_9,\nquestion_10: @local.answer_10",
                    "matchedExpression": "@local.answer_10",
                    "type": "local",
                    "fieldName": "answer_10"
                  }
                ],
                "_cleaned": [
                  {
                    "fullExpression": "click | set_data |\n_list_id: report_answers,\n_id: @fields.current_report_no,\nquestion_1: @local.answer_1,\nquestion_2: @local.answer_2,\nquestion_3: @local.answer_3,\nquestion_4: @local.answer_4,\nquestion_5: @local.answer_5,\nquestion_6: @local.answer_6,\nquestion_7: @local.answer_7,\nquestion_8: @local.answer_8,\nquestion_9: @local.answer_9,\nquestion_10: @local.answer_10",
                    "matchedExpression": "@fields.current_report_no",
                    "type": "fields",
                    "fieldName": "current_report_no"
                  },
                  {
                    "fullExpression": "click | set_data |\n_list_id: report_answers,\n_id: @fields.current_report_no,\nquestion_1: @local.answer_1,\nquestion_2: @local.answer_2,\nquestion_3: @local.answer_3,\nquestion_4: @local.answer_4,\nquestion_5: @local.answer_5,\nquestion_6: @local.answer_6,\nquestion_7: @local.answer_7,\nquestion_8: @local.answer_8,\nquestion_9: @local.answer_9,\nquestion_10: @local.answer_10",
                    "matchedExpression": "@local.answer_1",
                    "type": "local",
                    "fieldName": "answer_1"
                  },
                  {
                    "fullExpression": "click | set_data |\n_list_id: report_answers,\n_id: @fields.current_report_no,\nquestion_1: @local.answer_1,\nquestion_2: @local.answer_2,\nquestion_3: @local.answer_3,\nquestion_4: @local.answer_4,\nquestion_5: @local.answer_5,\nquestion_6: @local.answer_6,\nquestion_7: @local.answer_7,\nquestion_8: @local.answer_8,\nquestion_9: @local.answer_9,\nquestion_10: @local.answer_10",
                    "matchedExpression": "@local.answer_2",
                    "type": "local",
                    "fieldName": "answer_2"
                  },
                  {
                    "fullExpression": "click | set_data |\n_list_id: report_answers,\n_id: @fields.current_report_no,\nquestion_1: @local.answer_1,\nquestion_2: @local.answer_2,\nquestion_3: @local.answer_3,\nquestion_4: @local.answer_4,\nquestion_5: @local.answer_5,\nquestion_6: @local.answer_6,\nquestion_7: @local.answer_7,\nquestion_8: @local.answer_8,\nquestion_9: @local.answer_9,\nquestion_10: @local.answer_10",
                    "matchedExpression": "@local.answer_3",
                    "type": "local",
                    "fieldName": "answer_3"
                  },
                  {
                    "fullExpression": "click | set_data |\n_list_id: report_answers,\n_id: @fields.current_report_no,\nquestion_1: @local.answer_1,\nquestion_2: @local.answer_2,\nquestion_3: @local.answer_3,\nquestion_4: @local.answer_4,\nquestion_5: @local.answer_5,\nquestion_6: @local.answer_6,\nquestion_7: @local.answer_7,\nquestion_8: @local.answer_8,\nquestion_9: @local.answer_9,\nquestion_10: @local.answer_10",
                    "matchedExpression": "@local.answer_4",
                    "type": "local",
                    "fieldName": "answer_4"
                  },
                  {
                    "fullExpression": "click | set_data |\n_list_id: report_answers,\n_id: @fields.current_report_no,\nquestion_1: @local.answer_1,\nquestion_2: @local.answer_2,\nquestion_3: @local.answer_3,\nquestion_4: @local.answer_4,\nquestion_5: @local.answer_5,\nquestion_6: @local.answer_6,\nquestion_7: @local.answer_7,\nquestion_8: @local.answer_8,\nquestion_9: @local.answer_9,\nquestion_10: @local.answer_10",
                    "matchedExpression": "@local.answer_5",
                    "type": "local",
                    "fieldName": "answer_5"
                  },
                  {
                    "fullExpression": "click | set_data |\n_list_id: report_answers,\n_id: @fields.current_report_no,\nquestion_1: @local.answer_1,\nquestion_2: @local.answer_2,\nquestion_3: @local.answer_3,\nquestion_4: @local.answer_4,\nquestion_5: @local.answer_5,\nquestion_6: @local.answer_6,\nquestion_7: @local.answer_7,\nquestion_8: @local.answer_8,\nquestion_9: @local.answer_9,\nquestion_10: @local.answer_10",
                    "matchedExpression": "@local.answer_6",
                    "type": "local",
                    "fieldName": "answer_6"
                  },
                  {
                    "fullExpression": "click | set_data |\n_list_id: report_answers,\n_id: @fields.current_report_no,\nquestion_1: @local.answer_1,\nquestion_2: @local.answer_2,\nquestion_3: @local.answer_3,\nquestion_4: @local.answer_4,\nquestion_5: @local.answer_5,\nquestion_6: @local.answer_6,\nquestion_7: @local.answer_7,\nquestion_8: @local.answer_8,\nquestion_9: @local.answer_9,\nquestion_10: @local.answer_10",
                    "matchedExpression": "@local.answer_7",
                    "type": "local",
                    "fieldName": "answer_7"
                  },
                  {
                    "fullExpression": "click | set_data |\n_list_id: report_answers,\n_id: @fields.current_report_no,\nquestion_1: @local.answer_1,\nquestion_2: @local.answer_2,\nquestion_3: @local.answer_3,\nquestion_4: @local.answer_4,\nquestion_5: @local.answer_5,\nquestion_6: @local.answer_6,\nquestion_7: @local.answer_7,\nquestion_8: @local.answer_8,\nquestion_9: @local.answer_9,\nquestion_10: @local.answer_10",
                    "matchedExpression": "@local.answer_8",
                    "type": "local",
                    "fieldName": "answer_8"
                  },
                  {
                    "fullExpression": "click | set_data |\n_list_id: report_answers,\n_id: @fields.current_report_no,\nquestion_1: @local.answer_1,\nquestion_2: @local.answer_2,\nquestion_3: @local.answer_3,\nquestion_4: @local.answer_4,\nquestion_5: @local.answer_5,\nquestion_6: @local.answer_6,\nquestion_7: @local.answer_7,\nquestion_8: @local.answer_8,\nquestion_9: @local.answer_9,\nquestion_10: @local.answer_10",
                    "matchedExpression": "@local.answer_9",
                    "type": "local",
                    "fieldName": "answer_9"
                  },
                  {
                    "fullExpression": "click | set_data |\n_list_id: report_answers,\n_id: @fields.current_report_no,\nquestion_1: @local.answer_1,\nquestion_2: @local.answer_2,\nquestion_3: @local.answer_3,\nquestion_4: @local.answer_4,\nquestion_5: @local.answer_5,\nquestion_6: @local.answer_6,\nquestion_7: @local.answer_7,\nquestion_8: @local.answer_8,\nquestion_9: @local.answer_9,\nquestion_10: @local.answer_10",
                    "matchedExpression": "@local.answer_10",
                    "type": "local",
                    "fieldName": "answer_10"
                  }
                ],
                "params": {
                  "_id": [
                    {
                      "fullExpression": "@fields.current_report_no",
                      "matchedExpression": "@fields.current_report_no",
                      "type": "fields",
                      "fieldName": "current_report_no"
                    }
                  ],
                  "question_1": [
                    {
                      "fullExpression": "@local.answer_1",
                      "matchedExpression": "@local.answer_1",
                      "type": "local",
                      "fieldName": "answer_1"
                    }
                  ],
                  "question_2": [
                    {
                      "fullExpression": "@local.answer_2",
                      "matchedExpression": "@local.answer_2",
                      "type": "local",
                      "fieldName": "answer_2"
                    }
                  ],
                  "question_3": [
                    {
                      "fullExpression": "@local.answer_3",
                      "matchedExpression": "@local.answer_3",
                      "type": "local",
                      "fieldName": "answer_3"
                    }
                  ],
                  "question_4": [
                    {
                      "fullExpression": "@local.answer_4",
                      "matchedExpression": "@local.answer_4",
                      "type": "local",
                      "fieldName": "answer_4"
                    }
                  ],
                  "question_5": [
                    {
                      "fullExpression": "@local.answer_5",
                      "matchedExpression": "@local.answer_5",
                      "type": "local",
                      "fieldName": "answer_5"
                    }
                  ],
                  "question_6": [
                    {
                      "fullExpression": "@local.answer_6",
                      "matchedExpression": "@local.answer_6",
                      "type": "local",
                      "fieldName": "answer_6"
                    }
                  ],
                  "question_7": [
                    {
                      "fullExpression": "@local.answer_7",
                      "matchedExpression": "@local.answer_7",
                      "type": "local",
                      "fieldName": "answer_7"
                    }
                  ],
                  "question_8": [
                    {
                      "fullExpression": "@local.answer_8",
                      "matchedExpression": "@local.answer_8",
                      "type": "local",
                      "fieldName": "answer_8"
                    }
                  ],
                  "question_9": [
                    {
                      "fullExpression": "@local.answer_9",
                      "matchedExpression": "@local.answer_9",
                      "type": "local",
                      "fieldName": "answer_9"
                    }
                  ],
                  "question_10": [
                    {
                      "fullExpression": "@local.answer_10",
                      "matchedExpression": "@local.answer_10",
                      "type": "local",
                      "fieldName": "answer_10"
                    }
                  ]
                }
              }
            }
          },
          "_dynamicDependencies": {
            "@fields.current_report_no": [
              "action_list.0._raw",
              "action_list.0._cleaned",
              "action_list.0.params._id"
            ],
            "@local.answer_1": [
              "action_list.0._raw",
              "action_list.0._cleaned",
              "action_list.0.params.question_1"
            ],
            "@local.answer_2": [
              "action_list.0._raw",
              "action_list.0._cleaned",
              "action_list.0.params.question_2"
            ],
            "@local.answer_3": [
              "action_list.0._raw",
              "action_list.0._cleaned",
              "action_list.0.params.question_3"
            ],
            "@local.answer_4": [
              "action_list.0._raw",
              "action_list.0._cleaned",
              "action_list.0.params.question_4"
            ],
            "@local.answer_5": [
              "action_list.0._raw",
              "action_list.0._cleaned",
              "action_list.0.params.question_5"
            ],
            "@local.answer_6": [
              "action_list.0._raw",
              "action_list.0._cleaned",
              "action_list.0.params.question_6"
            ],
            "@local.answer_7": [
              "action_list.0._raw",
              "action_list.0._cleaned",
              "action_list.0.params.question_7"
            ],
            "@local.answer_8": [
              "action_list.0._raw",
              "action_list.0._cleaned",
              "action_list.0.params.question_8"
            ],
            "@local.answer_9": [
              "action_list.0._raw",
              "action_list.0._cleaned",
              "action_list.0.params.question_9"
            ],
            "@local.answer_10": [
              "action_list.0._raw",
              "action_list.0._cleaned",
              "action_list.0.params.question_10"
            ]
          }
        }
      ],
      "name": "display_group_27",
      "_nested_name": "display_group_27"
    }
  ],
  "_xlsxPath": "templates/report_PH.xlsx",
  "_sheetsFolderUrl": "https://drive.google.com/drive/u/0/folders/1SUErA3iOev9XiOkQfOmmiDHtvnKRY6Go"
}