{
  "flow_type": "global",
  "flow_name": "article_global",
  "status": "released",
  "rows": [
    {
      "type": "declare_global_constant",
      "name": "message_disclaimer"
    },
    {
      "type": "declare_global_constant",
      "name": "share_button_text",
      "value": "Share",
      "_translations": {
        "value": {
          "ph_fil": true
        }
      }
    },
    {
      "type": "declare_global_constant",
      "name": "supervisor_contact",
      "value": "[PHONE NUMBER]",
      "_translations": {
        "value": {}
      },
      "exclude_from_translation": true
    }
  ],
  "_source": {
    "name": "facilitator_ph_sheets",
    "path": "data/FacilitatorApp PH articles.xlsx",
    "url": "https://docs.google.com/spreadsheets/d/1I8ERt0SpuUxJXVIvYISg7YZ-3bZMdl94mtSZvRFxA_s"
  }
}